github_restore/__init__.py
github_restore/gitee.py
github_restore/github.py
github_restore/main.py
github_restore/parse_args.py
github_restore/restore.py
github_restore-1.0.0.dist-info/WHEEL
github_restore-1.0.0.dist-info/METADATA
github_restore-1.0.0.dist-info/entry_points.txt
github_restore-1.0.0.dist-info/RECORD
